circuit_rs-0.3.3.dist-info/METADATA
circuit_rs-0.3.3.dist-info/WHEEL
circuit_rs-0.3.3.dist-info/licenses/LICENSE
circuit_rs/__init__.py
circuit_rs/circuit_rs.cpython-313-darwin.so
circuit_rs-0.3.3.dist-info/RECORD
