Metadata-Version: 2.4
Name: circuit-rs
Version: 0.3.3
Classifier: Programming Language :: Rust
Classifier: Programming Language :: Python :: Implementation :: CPython
Classifier: Programming Language :: Python :: Implementation :: PyPy
Requires-Dist: numpy>=1.24.4
License-File: LICENSE
Summary: A library for doing efficient operations on neural circuits
Author: Ian Quah<itq@uw.edu>
Author-email: Ian Quah <itq@uw.edu>
License: MIT
Requires-Python: >=3.12
